minifetch/__init__.py
minifetch/custom.txt
minifetch/main.py
minifetch/ascii/arch.txt
minifetch/ascii/debian.txt
minifetch/ascii/elementary.txt
minifetch/ascii/endeavour.txt
minifetch/ascii/fedora.txt
minifetch/ascii/freebsd.txt
minifetch/ascii/gentoo.txt
minifetch/ascii/mac.txt
minifetch/ascii/manjaro.txt
minifetch/ascii/mint.txt
minifetch/ascii/nobara.txt
minifetch/ascii/pop.txt
minifetch/ascii/ubuntu.txt
minifetch/ascii/windows.txt
minifetch/ascii/zorin.txt
minifetch_tool-1.0.2.dist-info/licenses/LICENSE
minifetch_tool-1.0.2.dist-info/METADATA
minifetch_tool-1.0.2.dist-info/WHEEL
minifetch_tool-1.0.2.dist-info/entry_points.txt
minifetch_tool-1.0.2.dist-info/top_level.txt
minifetch_tool-1.0.2.dist-info/RECORD
